peaky/__init__.py
peaky/_doc.py
peaky/_main.py
peaky/_methods.py
peaky/_string.py
peaky-1.1.dist-info/LICENSE
peaky-1.1.dist-info/METADATA
peaky-1.1.dist-info/WHEEL
peaky-1.1.dist-info/top_level.txt
peaky-1.1.dist-info/RECORD
