Metadata-Version: 2.1
Name: peaky
Version: 1.1
Summary: peaky fits a single peak to a lorentian, gaussian or voigt profile
Home-page: https://github.com/piccolomo/peaky
Author: Savino Piccolomo
Author-email: piccolomo@gmail.com
License: MIT
Classifier: Development Status :: 4 - Beta
Classifier: License :: OSI Approved :: MIT License
Classifier: Programming Language :: Python
Classifier: Programming Language :: Python :: 3.5
Classifier: Programming Language :: Python :: 3.6
Classifier: Topic :: Software Development :: Libraries
Classifier: Topic :: Software Development :: Libraries :: Python Modules
Classifier: Intended Audience :: Developers
Classifier: Intended Audience :: End Users/Desktop
Requires-Python: >=3.5
License-File: LICENSE
Requires-Dist: numpy >=1.0
Requires-Dist: scipy >=1.0
